MANIFEST.in
README.rst
setup.py
pk1/__init__.py
pk1/remedy/__init__.py
pk1/remedy/ambari/__init__.py
pk1/remedy/ambari/client.py
pk1/remedy/ambari/host_clone.py
pk1/remedy/ambari/host_delete.py
pk1/remedy/ambari/service_start.py
pk1/remedy/ambari/stack.py
pk1_remedy.egg-info/PKG-INFO
pk1_remedy.egg-info/SOURCES.txt
pk1_remedy.egg-info/dependency_links.txt
pk1_remedy.egg-info/entry_points.txt
pk1_remedy.egg-info/requires.txt
pk1_remedy.egg-info/top_level.txt