Metadata-Version: 1.0
Name: pk1-remedy
Version: 0.0.8
Summary: Scripts to remedy vm images (of packone).
Home-page: https://github.com/cas-bigdatalab/packone_remedy
Author: Excel Wang
Author-email: wanghj@cnic.com
License: Apache-2.0 Licence
Keywords: pip,packone
Platform: any
